setup_server.py
common/__init__.py
common/decos.py
common/descryptors.py
common/errors.py
common/metaclasses.py
common/utils.py
common/variables.py
logs/__init__.py
logs/config_client_log.py
logs/config_server_log.py
server/__init__.py
server/add_user.py
server/config_window.py
server/core.py
server/database.py
server/main_window.py
server/remove_user.py
server/stat_window.py
server_for_messenger.egg-info/PKG-INFO
server_for_messenger.egg-info/SOURCES.txt
server_for_messenger.egg-info/dependency_links.txt
server_for_messenger.egg-info/requires.txt
server_for_messenger.egg-info/top_level.txt
unit_tests/__init__.py