Metadata-Version: 1.0
Name: server-for-messenger
Version: 0.0.1
Summary: server_for_messenger
Home-page: UNKNOWN
Author: Tina
Author-email: tina@yandex.ru
License: UNKNOWN
Platform: UNKNOWN
